{
    "informacoes_das_ferramentas": [
        {
            "ID": "0",
            "Nome": "InterpreTEA",
            "Area": "Lingua Portuguesa",
            "Ano": "2022",
            "Metodologia": "TEACCH",
            "Custo": "Não",
            "Disponibilidade": "Educapes",
            "Link": "http://educapes.capes.gov.br/handle/capes/701276"
        },
        {
            "ID": "1",
            "Nome": "Terapia da Linguagem e Cognição com MITA",
            "Area": "Diversas",
            "Ano": "2015",
            "Metodologia": "MITA",
            "Custo": "Não",
            "Disponibilidade": 
                "Android e IOS",
            "Link": "https://play.google.com/store/apps/details?id=com.imagiration.mita"
        },
        {
            "ID": "2",
            "Nome": "Jade Autism",
            "Area": "Diversas",
            "Ano": "2018",
            "Metodologia": "DTT",
            "Custo": "Não, porém apresenta versão paga.",
            "Disponibilidade": "Android e IOS",
            "Link": "https://play.google.com/store/apps/details?id=com.jadeautism.jadeautism"
        },
        {
            "ID": "3",
            "Nome": "AutiSpark: Autistas Jogos",
            "Area": "Diversas",
            "Ano": "2020",
            "Metodologia": "Não apresenta",
            "Custo": "R$36.99",
            "Disponibilidade": "Android e IOS",
            "Link": "https://play.google.com/store/apps/details?id=com.iz.autispark.kids.autism.games.special.needs.educational.learning.therapy.social.skills.speech"
        },
        {
            "ID": "4",
            "Nome": "123 Autismo",
            "Area": "Matemática",
            "Ano": "2018",
            "Metodologia": "Não apresenta",
            "Custo": "R$3.99",
            "Disponibilidade": "Android",
            "Link": "https://play.google.com/store/apps/details?id=com.dokye.umdoistresautismo"
        },
        {
            "ID": "5",
            "Nome": "AutApp - Autismo",
            "Area": "Matemática",
            "Ano": "2017",
            "Metodologia": "TEACCH",
            "Custo": "Não, porém apresenta versão paga.",
            "Disponibilidade": "Android",
            "Link": "https://play.google.com/store/apps/details?id=io.gabriel.hahn.autapp"
        },
        {
            "ID": "6",
            "Nome": "Contando o Autismo 123",
            "Area": "Matemática",
            "Ano": "2020",
            "Metodologia": "Não apresenta",
            "Custo": "Não",
            "Disponibilidade": "Android",
            "Link": "https://play.google.com/store/apps/details?id=com.Worldwide.count123"
        }
    ]
}